udk/__intit__.py
udk/filesystem.py
udk/tools.py
udk-0.0.2.dist-info/LICENSE
udk-0.0.2.dist-info/METADATA
udk-0.0.2.dist-info/WHEEL
udk-0.0.2.dist-info/top_level.txt
udk-0.0.2.dist-info/RECORD
